README.md
setup.py
bencode3/__init__.py
bencode3.egg-info/PKG-INFO
bencode3.egg-info/SOURCES.txt
bencode3.egg-info/dependency_links.txt
bencode3.egg-info/top_level.txt