Metadata-Version: 2.1
Name: bencode3
Version: 0.1.0
Summary: a simple bencode lib for python3
Home-page: https://bitbucket.org/tinyproxy/bencode3
Author: hschen
Author-email: pypi@haisong.me
License: UNKNOWN
Platform: UNKNOWN
Classifier: Programming Language :: Python :: 3
Classifier: License :: OSI Approved :: MIT License
Classifier: Operating System :: OS Independent
